fds/__init__.py
fds/sdk/__init__.py
fds/sdk/EventsandTranscripts/__init__.py
fds/sdk/EventsandTranscripts/api_client.py
fds/sdk/EventsandTranscripts/configuration.py
fds/sdk/EventsandTranscripts/exceptions.py
fds/sdk/EventsandTranscripts/model_utils.py
fds/sdk/EventsandTranscripts/rest.py
fds/sdk/EventsandTranscripts/api/__init__.py
fds/sdk/EventsandTranscripts/api/calendar_events_api.py
fds/sdk/EventsandTranscripts/api/events_audio_api.py
fds/sdk/EventsandTranscripts/api/meta_api.py
fds/sdk/EventsandTranscripts/api/near_real_time_transcripts_api.py
fds/sdk/EventsandTranscripts/api/transcripts_api.py
fds/sdk/EventsandTranscripts/apis/__init__.py
fds/sdk/EventsandTranscripts/model/__init__.py
fds/sdk/EventsandTranscripts/model/audio_by_date_request.py
fds/sdk/EventsandTranscripts/model/audio_by_file_name_request.py
fds/sdk/EventsandTranscripts/model/audio_by_ids_request.py
fds/sdk/EventsandTranscripts/model/audio_by_upload_time_request.py
fds/sdk/EventsandTranscripts/model/audio_request.py
fds/sdk/EventsandTranscripts/model/audio_request_data.py
fds/sdk/EventsandTranscripts/model/audio_request_meta.py
fds/sdk/EventsandTranscripts/model/audio_request_meta_pagination.py
fds/sdk/EventsandTranscripts/model/audio_response.py
fds/sdk/EventsandTranscripts/model/body.py
fds/sdk/EventsandTranscripts/model/body_nrt.py
fds/sdk/EventsandTranscripts/model/categories_response.py
fds/sdk/EventsandTranscripts/model/categories_response_data.py
fds/sdk/EventsandTranscripts/model/company_event_request.py
fds/sdk/EventsandTranscripts/model/company_event_request_data.py
fds/sdk/EventsandTranscripts/model/company_event_request_data_date_time.py
fds/sdk/EventsandTranscripts/model/company_event_request_data_universe.py
fds/sdk/EventsandTranscripts/model/company_event_response.py
fds/sdk/EventsandTranscripts/model/company_event_response_data.py
fds/sdk/EventsandTranscripts/model/document.py
fds/sdk/EventsandTranscripts/model/document_one.py
fds_sdk_eventsandtranscripts-2.1.1.dist-info/licenses/LICENSE
fds_sdk_eventsandtranscripts-2.1.1.dist-info/METADATA
fds_sdk_eventsandtranscripts-2.1.1.dist-info/WHEEL
fds_sdk_eventsandtranscripts-2.1.1.dist-info/top_level.txt
fds_sdk_eventsandtranscripts-2.1.1.dist-info/RECORD
